[2017-10-10 00:05:29.8154][TRACE][WebApi.CMApi_Message] 收到请求：
GET http://172.17.0.9:8999/CMApi/api/basic/account/testconnect


[2017-10-10 00:05:29.8200][TRACE][WebApi.CMApi_Message] 发送应答：
Access-Control-Allow-Origin: *
Access-Control-Allow-Headers: Origin, Content-Type, X-Requested-With, Accept
Access-Control-Allow-Methods: GET, PUT, POST, DELETE, HEAD

{
  "code": "0",
  "msg": "Welcome To CM Server"
}

[2017-10-10 00:05:34.0441][TRACE][WebApi.CMApi_Message] 收到请求：
GET http://172.16.168.205:9023/CMApi/api/basic/account/getuserstoragebycode?usertoken=91cdcdb906f7fdef4860047ba65371c7&code=admin
User-Agent: cpprestsdk/2.6.0
sobeyhive-http-site: S1
sobeyhive-http-system: MATERIALLIST
sobeyhive-http-token: 91cdcdb906f7fdef4860047ba65371c7
sobeyhive-http-tool: MLCLIENT
sobeyhive-http-usercode: admin
Host: 172.16.168.205:9023
ORIG_CLIENT_IP: 172.16.145.32
Connection: close


[2017-10-10 00:05:34.1259][TRACE][WebApi.CMApi_Message] 发送应答：
Access-Control-Allow-Origin: *
Access-Control-Allow-Headers: Origin, Content-Type, X-Requested-With, Accept
Access-Control-Allow-Methods: GET, PUT, POST, DELETE, HEAD

{
  "code": "0",
  "ext": {
    "storagesize": 5617817223168,
    "storageusage": 2387220741196,
    "storagewarningpct": 0.8
  }
}
