<?xml version="1.0" encoding="UTF-8"?>
<MPC>
	<Header>
		<Version>1.0</Version>
		<RequestID>9412f5681fd649bca162457f4e5917a0</RequestID>
		<RequestTime>2021-08-05T10:52:09</RequestTime>
		<RequestMQ>USELESS</RequestMQ>
	</Header>
	<Content>
		<MPCType>AssignTask</MPCType>
		<AssignTask>
			<BaseInfo>
				<TaskGUID>c442b47773f040f1bca04d6171d4bedf</TaskGUID>
				<TaskName>HDF 8CH MXF</TaskName>
				<TaskPriority>10</TaskPriority>
				<DispatchType>auto</DispatchType>
				<Controllable>1</Controllable>
			</BaseInfo>
			<TaskInfo>
				<Scope>ETClipAdditiveData</Scope>
				<Schema>ETClipAdditiveData</Schema>
				<Data>
					<ETClipAdditiveData>
						<CLIPGUID>0f50358782de44c988316af5e18d061e</CLIPGUID>
						<USERCODE>admin</USERCODE>
						<SYSTEM>CGW</SYSTEM>
						<FLOWTYPE>MXFToML</FLOWTYPE>
						<FLOWSUBTYPE>Import</FLOWSUBTYPE>
						<DELETEOLDFILE>1</DELETEOLDFILE>
						<OLDFILE>c:\HDF 8CH MXF.mxf</OLDFILE>
						<QUALITYTYPE>0</QUALITYTYPE>
						<TASKID>89</TASKID>
						<version>gen2</version>
					</ETClipAdditiveData>
				</Data>
			</TaskInfo>
			<TaskInfo>
				<Scope>tv_srcclipinfo</Scope>
				<Schema>tv_srcclipinfo</Schema>
				<Data>
					<SrcClipInfo>
						<DropFrame>0</DropFrame>
					</SrcClipInfo>
				</Data>
			</TaskInfo>
			<MediaFile>
				<GroupType>MXFToMlGType</GroupType>
				<MediaType>MXFToMlMType</MediaType>
				<FileName>c:\HDF 8CH MXF.mxf</FileName>
				<InPoint>0</InPoint>
				<OutPoint>-1</OutPoint>
			</MediaFile>
			<NotifyTarget>http://172.16.149.205:9023/CMApi/api/entity/clip/clipstorestr@POST</NotifyTarget>
			<TaskInfo>
				<Scope>ObjPath</Scope>
				<Schema>ObjPath</Schema>
				<Data>
					<CommonObjInfo>
						<HVDestDir>c:\</HVDestDir>
						<HADestDir>c:\</HADestDir>
						<LVDestDir>c:\</LVDestDir>
						<LADestDir>c:\</LADestDir>
					</CommonObjInfo>
				</Data>
			</TaskInfo>
			<MediaFile>
				<GroupType>high</GroupType>
				<MediaType>video</MediaType>
				<FileName>C:\high_video\c442b47773f040f1bca04d6171d4bedf\HDF_8CH_MXF_c442b47773f040f1bca04d6171d4bedf.mxf</FileName>
				<InPoint>0</InPoint>
				<OutPoint>305200000</OutPoint>
				<VerifyCode/>
				<FileParam>
					<FileFormat>2160</FileFormat>
					<VideoFormat>93</VideoFormat>
					<BitRate>50000000</BitRate>
					<FrameRate>25</FrameRate>
					<ScanMode>1</ScanMode>
					<ImageWidth>1920</ImageWidth>
					<ImageHeight>1080</ImageHeight>
					<KeyFrameRate>12</KeyFrameRate>
					<AudioFormat>1040</AudioFormat>
					<Channels>8</Channels>
					<SamplesPerSec>48000</SamplesPerSec>
					<BitsPerSample>24</BitsPerSample>
					<CCFormat>0</CCFormat>
					<Duration>305200000</Duration>
					<FileSize>229482080</FileSize>
					<DbeChannels>0</DbeChannels>
				</FileParam>
			</MediaFile>
			
			<JobType>mediatrans</JobType>
			<JobID>58241</JobID>
			<BreakResume>0</BreakResume>
			<JobInfo>
				<Scope>tv_transcodejobparam2</Scope>
				<Schema>sbtranscodejobparam2.xsd</Schema>
				<Data>
					<TranscodeJobParam2>
						<Src>
							<GroupType>MXFToMlGType</GroupType>
							<VideoMedia>MXFToMlMType</VideoMedia>
							<AudioMedia>
								<MediaType>MXFToMlMType</MediaType>
								<UseChannels>0</UseChannels>
								<MapAsTracks>0</MapAsTracks>
							</AudioMedia>
							<CCMedia/>
						</Src>
						<Option>
							<DeleteSource>0</DeleteSource>
							<OnTargetExist>1</OnTargetExist>
							<AddCleanInfo>0</AddCleanInfo>
							<AnalyzeTarget>1</AnalyzeTarget>
							<CreateOtcFile>-1</CreateOtcFile>
							<AudioMute>1</AudioMute>
						</Option>
						<Obj>
							<GroupType>low</GroupType>
							<MediaType>video</MediaType>
							<PathFormat>c:\?taskguid\?taskname_?taskguid_?filetype_?mediatype.?ext</PathFormat>
							<UseTracks>1,2,3,4,5,6,7,8,</UseTracks>
							<OutputIdxXml>0</OutputIdxXml>
							<UseAudioMix>0</UseAudioMix>
							<CodecParam>
								<FileFormat>2103</FileFormat>
								<VideoFormat>37</VideoFormat>
								<FileDispAspectRatio>0</FileDispAspectRatio>
								<CodecDispAspectRatio>0</CodecDispAspectRatio>
								<BitRate>1500000</BitRate>
								<FrameRate>AS_SRC</FrameRate>
								<ImageWidth>480</ImageWidth>
								<ImageHeight>270</ImageHeight>
								<UseAspectRatioSetting>1</UseAspectRatioSetting>
								<KeyFrameRate>25</KeyFrameRate>
								<AudioFormat>1047</AudioFormat>
								<SamplesPerSec>48000</SamplesPerSec>
								<BitsPerSample>16</BitsPerSample>
								<CCFormat>0</CCFormat>
								<SpecialParam>
									<![CDATA[<SpecialParam><VideoParam><interlace>3</interlace></VideoParam></SpecialParam>]]></SpecialParam>
							</CodecParam>
						</Obj>
						<Obj>
							<GroupType>low</GroupType>
							<MediaType>audio1</MediaType>
							<PathFormat>c:\?taskguid\?taskname_?taskguid_?filetype_?mediatype.?ext</PathFormat>
							<UseTracks>1,2,</UseTracks>
							<OutputIdxXml>0</OutputIdxXml>
							<UseAudioMix>0</UseAudioMix>
							<CodecParam>
								<FileFormat>2323</FileFormat>
								<VideoFormat>0</VideoFormat>
								<FileDispAspectRatio>0</FileDispAspectRatio>
								<CodecDispAspectRatio>0</CodecDispAspectRatio>
								<AudioFormat>1043</AudioFormat>
								<SamplesPerSec>48000</SamplesPerSec>
								<BitsPerSample>16</BitsPerSample>
								<CCFormat>0</CCFormat>
								<SpecialParam>
									<![CDATA[<SpecialParam><VideoParam><interlace>1</interlace></VideoParam></SpecialParam>]]></SpecialParam>
							</CodecParam>
						</Obj>
						<Obj>
							<GroupType>low</GroupType>
							<MediaType>audio2</MediaType>
							<PathFormat>c:\?taskguid\?taskname_?taskguid_?filetype_?mediatype.?ext</PathFormat>
							<UseTracks>3,4,</UseTracks>
							<OutputIdxXml>0</OutputIdxXml>
							<UseAudioMix>0</UseAudioMix>
							<CodecParam>
								<FileFormat>2323</FileFormat>
								<VideoFormat>0</VideoFormat>
								<FileDispAspectRatio>0</FileDispAspectRatio>
								<CodecDispAspectRatio>0</CodecDispAspectRatio>
								<AudioFormat>1043</AudioFormat>
								<SamplesPerSec>48000</SamplesPerSec>
								<BitsPerSample>16</BitsPerSample>
								<CCFormat>0</CCFormat>
								<SpecialParam>
									<![CDATA[<SpecialParam><VideoParam><interlace>1</interlace></VideoParam></SpecialParam>]]></SpecialParam>
							</CodecParam>
						</Obj>
						<Obj>
							<GroupType>low</GroupType>
							<MediaType>audio3</MediaType>
							<PathFormat>c:\?taskguid\?taskname_?taskguid_?filetype_?mediatype.?ext</PathFormat>
							<UseTracks>5,6,</UseTracks>
							<OutputIdxXml>0</OutputIdxXml>
							<UseAudioMix>0</UseAudioMix>
							<CodecParam>
								<FileFormat>2323</FileFormat>
								<VideoFormat>0</VideoFormat>
								<FileDispAspectRatio>0</FileDispAspectRatio>
								<CodecDispAspectRatio>0</CodecDispAspectRatio>
								<AudioFormat>1043</AudioFormat>
								<SamplesPerSec>48000</SamplesPerSec>
								<BitsPerSample>16</BitsPerSample>
								<CCFormat>0</CCFormat>
								<SpecialParam>
									<![CDATA[<SpecialParam><VideoParam><interlace>1</interlace></VideoParam></SpecialParam>]]></SpecialParam>
							</CodecParam>
						</Obj>
						<Obj>
							<GroupType>low</GroupType>
							<MediaType>audio4</MediaType>
							<PathFormat>c:\?taskguid\?taskname_?taskguid_?filetype_?mediatype.?ext</PathFormat>
							<UseTracks>7,8,</UseTracks>
							<OutputIdxXml>0</OutputIdxXml>
							<UseAudioMix>0</UseAudioMix>
							<CodecParam>
								<FileFormat>2323</FileFormat>
								<VideoFormat>0</VideoFormat>
								<FileDispAspectRatio>0</FileDispAspectRatio>
								<CodecDispAspectRatio>0</CodecDispAspectRatio>
								<AudioFormat>1043</AudioFormat>
								<SamplesPerSec>48000</SamplesPerSec>
								<BitsPerSample>16</BitsPerSample>
								<CCFormat>0</CCFormat>
								<SpecialParam>
									<![CDATA[<SpecialParam><VideoParam><interlace>1</interlace></VideoParam></SpecialParam>]]></SpecialParam>
							</CodecParam>
						</Obj>
					</TranscodeJobParam2>
				</Data>
			</JobInfo>
		</AssignTask>
	</Content>
</MPC>
